hostnamegen/__init__.py
hostnamegen/base.py
hostnamegen/exceptions.py
hostnamegen/patterns.py
hostnamegen-0.9.0.dist-info/LICENSE
hostnamegen-0.9.0.dist-info/METADATA
hostnamegen-0.9.0.dist-info/WHEEL
hostnamegen-0.9.0.dist-info/entry_points.txt
hostnamegen-0.9.0.dist-info/top_level.txt
hostnamegen-0.9.0.dist-info/RECORD
