Metadata-Version: 2.1
Name: hostnamegen
Version: 0.9.0
Summary: Random host name generator
Home-page: https://github.com/tasooshi/hostnamegen
Author: tasooshi
Author-email: tasooshi@pm.me
License: BSD 3-Clause "New" or "Revised" License (BSD-3-Clause)
Keywords: host,name,generator,random
Platform: UNKNOWN
Classifier: Development Status :: 4 - Beta
Classifier: Topic :: Utilities
Classifier: License :: OSI Approved :: BSD License
Classifier: Programming Language :: Python :: 2.7
Classifier: Programming Language :: Python :: 3.6
Classifier: Programming Language :: Python :: 3.7
